LICENSE.txt
README.md
setup.cfg
setup.py
pygoogle_image/__init__.py
pygoogle_image/image.py
pygoogle_image.egg-info/PKG-INFO
pygoogle_image.egg-info/SOURCES.txt
pygoogle_image.egg-info/dependency_links.txt
pygoogle_image.egg-info/not-zip-safe
pygoogle_image.egg-info/requires.txt
pygoogle_image.egg-info/top_level.txt