Metadata-Version: 2.1
Name: pygoogle-image
Version: 1.0.0
Summary: the package downloads images from google images
Home-page: https://github.com/Arthurpinange/pygoogle_image
Author: Arthur Pinangé
Author-email: arthur.pinange@gmail.com
License: MIT
Platform: UNKNOWN
